oidc_hub/__init__.py
oidc_hub/urls.py
oidc_hub/accounts/__init__.py
oidc_hub/accounts/admin.py
oidc_hub/accounts/apps.py
oidc_hub/accounts/models.py
oidc_hub/accounts/scopes.py
oidc_hub/accounts/tests.py
oidc_hub/accounts/urls.py
oidc_hub/accounts/views.py
oidc_hub/accounts/locale/en/LC_MESSAGES/django.mo
oidc_hub/accounts/locale/en/LC_MESSAGES/django.po
oidc_hub/accounts/locale/fr/LC_MESSAGES/django.mo
oidc_hub/accounts/locale/fr/LC_MESSAGES/django.po
oidc_hub/accounts/migrations/0001_initial.py
oidc_hub/accounts/migrations/__init__.py
oidc_hub/accounts/templates/accounts/login.j2
oidc_hub/accounts/templates/accounts/signup.j2
oidc_hub/accounts/templates/accounts/emails/invitation.j2
oidc_hub/accounts/templates/accounts/emails/invitation.txt
oidc_hub/accounts/templates/accounts/pass/change.j2
oidc_hub/accounts/templates/accounts/pass/change_done.j2
oidc_hub/accounts/templates/accounts/pass/reset.j2
oidc_hub/accounts/templates/accounts/pass/reset_done.j2
oidc_hub/accounts/templates/accounts/pass/reset_email.j2
oidc_hub/accounts/templates/admin/base.html
oidc_hub/accounts/templatetags/safe_file_content.py
oidc_hub/admin/__init__.py
oidc_hub/admin/apps.py
oidc_hub/admin/sites.py
oidc_hub/admin/locale/en/LC_MESSAGES/django.mo
oidc_hub/admin/locale/en/LC_MESSAGES/django.po
oidc_hub/admin/locale/fr/LC_MESSAGES/django.mo
oidc_hub/admin/locale/fr/LC_MESSAGES/django.po
oidc_hub-0.8.dist-info/LICENSE.md
oidc_hub-0.8.dist-info/WHEEL
oidc_hub-0.8.dist-info/METADATA
oidc_hub-0.8.dist-info/RECORD
