Metadata-Version: 2.1
Name: oidc_hub
Version: 0.8
Summary: OIDCHub: Identity provider for the mortals 🪪
Keywords: 
Author-email: opsocket <opsocket@pm.me>
Classifier: Development Status :: 4 - Beta
Classifier: Intended Audience :: Developers
Classifier: License :: OSI Approved :: GNU Affero General Public License v3 or later (AGPLv3+)
Classifier: Operating System :: OS Independent
Classifier: Programming Language :: Python :: 3
Classifier: Topic :: Software Development :: Libraries
Classifier: Topic :: Software Development
Classifier: Topic :: System :: Systems Administration
Classifier: Framework :: Django
Requires-Dist: django==4.2
Requires-Dist: django-oidc-provider
Requires-Dist: django-extensions ; extra == "dev"
Requires-Dist: black ; extra == "dev"
Requires-Dist: flake8 ; extra == "dev"
Requires-Dist: flit ; extra == "dev"
Requires-Dist: build ; extra == "dev"
Requires-Dist: twine ; extra == "dev"
Project-URL: Repository, https://gitlab.com/opsocket/oidc-hub.git
Provides-Extra: dev
